MANIFEST.in
license.txt
pyproject.toml
readme.md
setup.cfg
setup.py
reticulator/__init__.py
reticulator/core.py
reticulator/reticulator.py
reticulator/reticulator.pyi
reticulator/stubby.py
reticulator.egg-info/PKG-INFO
reticulator.egg-info/SOURCES.txt
reticulator.egg-info/dependency_links.txt
reticulator.egg-info/requires.txt
reticulator.egg-info/top_level.txt
test/test.py