Metadata-Version: 2.4
Name: reticulator
Version: 1.0.1
Summary: Reticulator is a library for interacting with Minecraft Bedrock Add-ons programmatically.
License: MIT License
Keywords: MINECRAFT,BEDROCK-EDITION,BEDROCK-ADDONS
Classifier: Development Status :: 5 - Production/Stable
Classifier: Intended Audience :: Developers
Classifier: Topic :: Software Development :: Libraries
Classifier: License :: OSI Approved :: MIT License
Classifier: Programming Language :: Python :: 3
License-File: license.txt
Requires-Dist: dpath==2.1.2
Dynamic: license-file
